kicad_to_openpnp/__init__.py
kicad_to_openpnp/board_to_packages.py
kicad_to_openpnp/board_to_parts.py
kicad_to_openpnp/cli_utils.py
kicad_to_openpnp/const.py
kicad_to_openpnp/footprint_to_package.py
kicad_to_openpnp/kicad_utils.py
kicad_to_openpnp/xml_utils.py
kicad_to_openpnp-0.2.0.dist-info/LICENSE
kicad_to_openpnp-0.2.0.dist-info/METADATA
kicad_to_openpnp-0.2.0.dist-info/WHEEL
kicad_to_openpnp-0.2.0.dist-info/entry_points.txt
kicad_to_openpnp-0.2.0.dist-info/RECORD
