Metadata-Version: 2.3
Name: kicad-to-openpnp
Version: 0.2.0
Summary: Transform a KiCad footprint into a OpenPnP package
License: MIT
Author: Maciej Małecki
Author-email: <me@mmalecki.com>
Requires-Python: >= 3.10
Classifier: License :: OSI Approved :: MIT License
Classifier: Programming Language :: Python :: 3
Classifier: Programming Language :: Python :: 3.10
Classifier: Programming Language :: Python :: 3.11
Classifier: Programming Language :: Python :: 3.12
Classifier: Programming Language :: Python :: 3.13
Requires-Dist: cadquery-ocp-novtk (>=7.8.1.1,<8.0.0.0)
Requires-Dist: colorlog (>=6.9.0,<7.0.0)
Requires-Dist: sexpdata (>=1.0.2,<2.0.0)
Project-URL: Repository, https://github.com/mmalecki/kicad-to-openpnp
